CHANGES.rst
LICENSE
MANIFEST.in
README.rst
requirements.txt
setup.py
tapes/__init__.py
tapes/meta.py
tapes/registry.py
tapes/reservoir.py
tapes.egg-info/PKG-INFO
tapes.egg-info/SOURCES.txt
tapes.egg-info/dependency_links.txt
tapes.egg-info/requires.txt
tapes.egg-info/top_level.txt
tapes.egg-info/zip-safe
tapes/distributed/__init__.py
tapes/distributed/counter.py
tapes/distributed/histogram.py
tapes/distributed/message.py
tapes/distributed/meter.py
tapes/distributed/proxy.py
tapes/distributed/registry.py
tapes/distributed/timer.py
tapes/local/__init__.py
tapes/local/average.py
tapes/local/counter.py
tapes/local/gauge.py
tapes/local/histogram.py
tapes/local/meter.py
tapes/local/stats.py
tapes/local/timer.py
tapes/reporting/__init__.py
tapes/reporting/http.py
tapes/reporting/statsd.py
tapes/reporting/stream.py
tapes/reporting/tornado/__init__.py
tapes/reporting/tornado/statsd.py
tapes/reporting/tornado/stream.py