Metadata-Version: 1.1
Name: tapes
Version: 0.3
Summary: Metrics for Python processes
Home-page: https://www.github.com/emilssolmanis/tapes
Author: Emils Solmanis
Author-email: emils.solmanis@gmail.com
License: Apache License (2.0)
Keywords: metrics
Platform: UNKNOWN
Classifier: Development Status :: 3 - Alpha
Classifier: License :: OSI Approved :: Apache Software License
Classifier: Programming Language :: Python :: 2.7
Classifier: Programming Language :: Python :: 3
Classifier: Programming Language :: Python :: Implementation :: PyPy
Classifier: Topic :: System :: Monitoring
